twitch_archiver-4.4.5.dist-info/licenses/LICENSE
twitcharchiver/__init__.py
twitcharchiver/api.py
twitcharchiver/arguments.py
twitcharchiver/channel.py
twitcharchiver/configuration.py
twitcharchiver/database.py
twitcharchiver/downloader.py
twitcharchiver/exceptions.py
twitcharchiver/logger.py
twitcharchiver/processing.py
twitcharchiver/twitch.py
twitcharchiver/utils.py
twitcharchiver/vod.py
twitcharchiver/downloaders/chat.py
twitcharchiver/downloaders/highlight.py
twitcharchiver/downloaders/realtime.py
twitcharchiver/downloaders/stream.py
twitcharchiver/downloaders/video.py
twitch_archiver-4.4.5.dist-info/METADATA
twitch_archiver-4.4.5.dist-info/WHEEL
twitch_archiver-4.4.5.dist-info/entry_points.txt
twitch_archiver-4.4.5.dist-info/top_level.txt
twitch_archiver-4.4.5.dist-info/RECORD
