Metadata-Version: 2.4
Name: twitch-archiver
Version: 4.4.5
Summary: A simple, fast, platform-independent tool for downloading Twitch streams, videos, and chat logs.
Author-email: Brisppy <brisppy@protonmail.com>
License-Expression: GPL-3.0-or-later
Project-URL: Homepage, https://github.com/Brisppy/twitch-archiver
Project-URL: Bug Tracker, https://github.com/Brisppy/twitch-archiver/issues
Classifier: Programming Language :: Python :: 3
Classifier: Operating System :: OS Independent
Requires-Python: >=3.9
License-File: LICENSE
Requires-Dist: requests>=2.28.0
Requires-Dist: m3u8>=0.3.12
Dynamic: license-file
